{
  "id": 19,
  "title": "Conditional formatting",
  "description": "Define a conditional formatting rule for cells C7-11 so values greater than 200 are displayed in red but others in green.",
  "group": "C",
  "resets": 0,
  "language": "ENGLISH",
  "taskNumber": 17,
  "startTimeWatching": "2024-01-22T12:46:22.944Z",
  "endTimeWatching": "2024-01-22T12:47:26.317Z",
  "timeWatching": 63373,
  "startTimeDrawing": "2024-01-22T12:47:26.317Z",
  "endTimeDrawing": "2024-01-22T12:48:04.586Z",
  "timeDrawing": 38269
}